{
    "stream": {
        "stream": [
            "scatter", 
            "bar", 
            "histogram", 
            "box", 
            "heatmap", 
            "contour", 
            "histogram2d", 
            "histogram2dcontour", 
            "area", 
            "scatter3d", 
            "surface"
        ]
    }, 
    "scene": {
        "scene": [
            "layout"
        ]
    }, 
    "surface": {}, 
    "radialaxis": {
        "radialaxis": [
            "layout"
        ]
    }, 
    "marker": {
        "marker": [
            "scatter", 
            "bar", 
            "histogram", 
            "box", 
            "area", 
            "scatter3d"
        ]
    }, 
    "font": {
        "tickfont": [
            "colorbar", 
            "xaxis", 
            "yaxis", 
            "zaxis"
        ], 
        "textfont": [
            "scatter", 
            "scatter3d"
        ], 
        "font": [
            "layout", 
            "legend", 
            "annotation"
        ], 
        "titlefont": [
            "colorbar", 
            "xaxis", 
            "yaxis", 
            "zaxis", 
            "layout"
        ]
    }, 
    "angularaxis": {
        "angularaxis": [
            "layout"
        ]
    }, 
    "contour": {}, 
    "error_x": {
        "error_x": [
            "scatter", 
            "bar", 
            "histogram", 
            "scatter3d"
        ]
    }, 
    "error_y": {
        "error_y": [
            "scatter", 
            "bar", 
            "histogram", 
            "scatter3d"
        ]
    }, 
    "error_z": {
        "error_z": [
            "scatter3d"
        ]
    }, 
    "area": {}, 
    "annotation": {}, 
    "heatmap": {}, 
    "zaxis": {
        "zaxis": [
            "scene"
        ]
    }, 
    "contours": {
        "contours": [
            "contour", 
            "histogram2dcontour"
        ]
    }, 
    "xaxis": {
        "xaxis": [
            "scene", 
            "layout"
        ]
    }, 
    "figure": {}, 
    "scatter3d": {}, 
    "annotations": {
        "annotations": [
            "layout"
        ]
    }, 
    "histogram2d": {}, 
    "xbins": {
        "xbins": [
            "histogram", 
            "histogram2d", 
            "histogram2dcontour"
        ]
    }, 
    "layout": {
        "layout": [
            "figure"
        ]
    }, 
    "line": {
        "line": [
            "scatter", 
            "box", 
            "contour", 
            "histogram2dcontour", 
            "scatter3d", 
            "marker"
        ]
    }, 
    "histogram": {}, 
    "data": {
        "data": [
            "figure"
        ]
    }, 
    "legend": {
        "legend": [
            "layout"
        ]
    }, 
    "ybins": {
        "ybins": [
            "histogram", 
            "histogram2d", 
            "histogram2dcontour"
        ]
    }, 
    "box": {}, 
    "bar": {}, 
    "yaxis": {
        "yaxis": [
            "scene", 
            "layout"
        ]
    }, 
    "margin": {
        "margin": [
            "layout"
        ]
    }, 
    "colorbar": {
        "colorbar": [
            "heatmap", 
            "contour", 
            "histogram2d", 
            "histogram2dcontour"
        ]
    }, 
    "histogram2dcontour": {}, 
    "scatter": {}
}